geograpy4/__init__.py
geograpy4/extraction.py
geograpy4/geocoder.py
geograpy4/places.py
geograpy4/data/GeoLite2-City-Locations.csv
geograpy4/data/ISO3166ErrorDictionary.csv
geograpy4-1.0.2.dist-info/LICENSE.md
geograpy4-1.0.2.dist-info/METADATA
geograpy4-1.0.2.dist-info/WHEEL
geograpy4-1.0.2.dist-info/top_level.txt
geograpy4-1.0.2.dist-info/RECORD
